libretto_openai/__init__.py
libretto_openai/background.py
libretto_openai/client.py
libretto_openai/completions.py
libretto_openai/completions_impl.py
libretto_openai/pii/__init__.py
libretto_openai/pii/data/__init__.py
libretto_openai/pii/data/names.json
libretto_openai/pii/data/names.json.LICENSE
libretto_openai/pii/name_recognizer.py
libretto_openai/pii/nlp.py
libretto_openai/pii/redactor.py
libretto_openai/pii/street_address_recognizer.py
libretto_openai/py.typed
libretto_openai/session.py
libretto_openai/template.py
libretto_openai/types.py
libretto_openai-1.1.3.dist-info/AUTHORS.rst
libretto_openai-1.1.3.dist-info/LICENSE
libretto_openai-1.1.3.dist-info/METADATA
libretto_openai-1.1.3.dist-info/WHEEL
libretto_openai-1.1.3.dist-info/RECORD
