Metadata-Version: 2.3
Name: libretto-openai
Version: 1.1.3
Summary: Wrapper library for openai to send events to Libretto
License: MIT
Author: Alec Flett
Author-email: alecf@thegp.com
Requires-Python: >=3.10,<4.0
Classifier: License :: OSI Approved :: MIT License
Classifier: Programming Language :: Python :: 3
Classifier: Programming Language :: Python :: 3.10
Classifier: Programming Language :: Python :: 3.11
Classifier: Programming Language :: Python :: 3.12
Classifier: Programming Language :: Python :: 3.13
Requires-Dist: aiohttp (>=3.8.5,<4.0.0)
Requires-Dist: openai (>=1.71.0,<2.0.0)
Requires-Dist: presidio-analyzer (>=2.2.33,<3.0.0)
Requires-Dist: presidio-anonymizer (>=2.2.33,<3.0.0)
